{
  "parent": "minecraft:recipes/root",
  "criteria": {
    "has_coffee_beans_roasted": {
      "conditions": {
        "items": [
          {
            "items": [
              "ravencoffee:coffee_beans_roasted"
            ]
          }
        ]
      },
      "trigger": "minecraft:inventory_changed"
    },
    "has_the_recipe": {
      "conditions": {
        "recipe": "minecraft:coffee_beans_roasted_from_block"
      },
      "trigger": "minecraft:recipe_unlocked"
    }
  },
  "requirements": [
    [
      "has_coffee_beans_roasted",
      "has_the_recipe"
    ]
  ],
  "rewards": {
    "recipes": [
      "minecraft:coffee_beans_roasted_from_block"
    ]
  },
  "sends_telemetry_event": false
}